selcom_apigw_client/__init__.py
selcom_apigw_client/apigwClient.py
selcom_apigw_client-1.0.1.dist-info/LICENSE.txt
selcom_apigw_client-1.0.1.dist-info/METADATA
selcom_apigw_client-1.0.1.dist-info/WHEEL
selcom_apigw_client-1.0.1.dist-info/top_level.txt
selcom_apigw_client-1.0.1.dist-info/RECORD
