Metadata-Version: 2.1
Name: selcom-apigw-client
Version: 1.0.1
Summary: A small example package
Author-email: Dev <dev@selcom.net>
Project-URL: Homepage, https://developers.selcommobile.com/
Classifier: Programming Language :: Python :: 3
Classifier: License :: OSI Approved :: MIT License
Classifier: Operating System :: OS Independent
Requires-Python: >=3.7
License-File: LICENSE.txt
Requires-Dist: requests
